{
  "file": "d:\\rutasmorelia\\data\\processed\\matched\\ruta-roja-2-villas-del-sol.geojson",
  "route_id": "ruta-roja-2-villas-del-sol",
  "route_name": "Roja 2 Villas del Sol",
  "status": "approved",
  "publishable": true,
  "issues": [],
  "directions": [
    {
      "direction": "ida",
      "qa_status": "approved",
      "validator": "valhalla+osrm",
      "avg_snap_m": 1.89,
      "max_snap_m": 7.41,
      "confidence": 0.992,
      "issues": []
    },
    {
      "direction": "vuelta",
      "qa_status": "approved",
      "validator": "valhalla+osrm",
      "avg_snap_m": 2.2,
      "max_snap_m": 8.96,
      "confidence": 0.99,
      "issues": []
    }
  ],
  "pass": true,
  "validated_at": "2026-07-09T11:25:47.514955+00:00"
}